HELML/__init__.py
HELML/_helml.py
HELML/_version.py
HELML-0.1.9.dist-info/LICENSE
HELML-0.1.9.dist-info/METADATA
HELML-0.1.9.dist-info/WHEEL
HELML-0.1.9.dist-info/top_level.txt
HELML-0.1.9.dist-info/RECORD
