Metadata-Version: 2.1
Name: HELML
Version: 0.1.9
Summary: Encoding-decoding HELML format
Home-page: https://github.com/dynoser/HELML/tree/master/Python
Author: AlexanderJer
Author-email: alexierusalim@gmail.com
License: MIT
Classifier: Development Status :: 3 - Alpha
Classifier: Intended Audience :: Developers
Classifier: License :: OSI Approved :: MIT License
Classifier: Programming Language :: Python :: 3
Classifier: Programming Language :: Python :: 3.6
Classifier: Programming Language :: Python :: 3.7
Classifier: Programming Language :: Python :: 3.8
Classifier: Programming Language :: Python :: 3.9
License-File: LICENSE
